setup.cfg
setup.py
calculo_irrf/__init__.py
calculo_irrf.egg-info/PKG-INFO
calculo_irrf.egg-info/SOURCES.txt
calculo_irrf.egg-info/dependency_links.txt
calculo_irrf.egg-info/top_level.txt