Metadata-Version: 1.0
Name: calculo-irrf
Version: 0.1
Summary: Cálculo de IRRF
Home-page: https://github.com/batistasan/calculo_irrf
Author: João Batista dos Santos Filho
Author-email: joaobatista.sf@hotmail.com
License: MIT License
Keywords: calculo irrf irpf receita federal
Platform: UNKNOWN
